{"cameraMode":{"drawMode":0,"name":"Shaded","section":"Shading Mode"},"sceneLighting":true,"audioPlay":false,"sceneViewState":{"showFog":true,"showMaterialUpdate":false,"showSkybox":true,"showFlares":true,"showImageEffects":true,"showParticleSystems":true},"in2DMode":false,"pivot":{"x":-1.3177647590637208,"y":2.603821277618408,"z":24.80478286743164},"rotation":{"x":0.00001153458833869081,"y":-0.9918619990348816,"z":0.12746462225914002,"w":-0.000024536868295399472},"size":10.998295783996582,"orthographic":false}